autoinject/__init__.py
autoinject/_tests.py
autoinject/class_registry.py
autoinject/context_manager.py
autoinject/informants.py
autoinject/injection.py
autoinject-1.3.3.dist-info/LICENSE
autoinject-1.3.3.dist-info/METADATA
autoinject-1.3.3.dist-info/WHEEL
autoinject-1.3.3.dist-info/top_level.txt
autoinject-1.3.3.dist-info/RECORD
