Metadata-Version: 2.1
Name: autoinject
Version: 1.3.3
Summary: Automated dependency injection for Python
Home-page: https://github.com/turnbullerin/autoinject
Author: Erin Turnbull
Author-email: erin.a.turnbull@gmail.com
Project-URL: Bug Tracker, https://github.com/turnbullerin/autoinject/issues
Project-URL: Documentation, https://autoinject.readthedocs.io/en/latest/
Classifier: Programming Language :: Python :: 3
Classifier: License :: OSI Approved :: MIT License
Classifier: Operating System :: OS Independent
Requires-Python: >=3.7
License-File: LICENSE
Requires-Dist: importlib-metadata ; python_version < "3.8"
